tracklang/__init__.py
tracklang/cli.py
tracklang/translator.py
tracklang-0.2.1.dist-info/licenses/LICENSE
tracklang-0.2.1.dist-info/METADATA
tracklang-0.2.1.dist-info/WHEEL
tracklang-0.2.1.dist-info/entry_points.txt
tracklang-0.2.1.dist-info/top_level.txt
tracklang-0.2.1.dist-info/RECORD
