Metadata-Version: 2.4
Name: tracklang
Version: 0.2.1
Summary: A TrackMania-themed syntax wrapper for Python
Author: Melodii7785
License: MIT
Classifier: Programming Language :: Python :: 3
Classifier: License :: OSI Approved :: MIT License
Classifier: Intended Audience :: Developers
Classifier: Topic :: Software Development :: Interpreters
Classifier: Topic :: Software Development :: Build Tools
Requires-Python: >=3.8
License-File: LICENSE
Dynamic: license-file
